{
    "interactionModel": {
        "languageModel": {
            "invocationName": "mis notas",
            "intents": [
                {
                    "name": "AMAZON.CancelIntent",
                    "samples": []
                },
                {
                    "name": "AMAZON.HelpIntent",
                    "samples": []
                },
                {
                    "name": "AMAZON.StopIntent",
                    "samples": []
                },
                {
                    "name": "AMAZON.NavigateHomeIntent",
                    "samples": []
                },
                {
                    "name": "NewNoteIntent",
                    "slots": [
                        {
                            "name": "note",
                            "type": "AMAZON.SearchQuery"
                        }
                    ],
                    "samples": [
                        "pon {note}",
                        "escribe {note}",
                        "añade {note}"
                    ]
                },
                {
                    "name": "ListNotesIntent",
                    "slots": [],
                    "samples": [
                        "dime mis notas",
                        "lista"
                    ]
                },
                {
                    "name": "AMAZON.MoreIntent",
                    "samples": []
                },
                {
                    "name": "AMAZON.NextIntent",
                    "samples": []
                },
                {
                    "name": "AMAZON.PreviousIntent",
                    "samples": []
                }
            ],
            "types": []
        }
    }
}